quantmsrescore/__init__.py
quantmsrescore/alphapeptdeep.py
quantmsrescore/annotator.py
quantmsrescore/constants.py
quantmsrescore/deeplc.py
quantmsrescore/exceptions.py
quantmsrescore/idxmlreader.py
quantmsrescore/logging_config.py
quantmsrescore/model_downloader.py
quantmsrescore/ms2_model_manager.py
quantmsrescore/ms2pip.py
quantmsrescore/ms2rescore.py
quantmsrescore/openms.py
quantmsrescore/psm_clean.py
quantmsrescore/rescoring.py
quantmsrescore/sage_feature.py
quantmsrescore/snr.py
quantmsrescore/transfer_learning.py
quantmsrescore/utils.py
quantms_rescoring-0.0.14.dist-info/METADATA
quantms_rescoring-0.0.14.dist-info/WHEEL
quantms_rescoring-0.0.14.dist-info/entry_points.txt
quantms_rescoring-0.0.14.dist-info/licenses/LICENSE
quantms_rescoring-0.0.14.dist-info/RECORD
