Metadata-Version: 2.4
Name: quantms-rescoring
Version: 0.0.14
Summary: quantms-rescoring: Python scripts and helpers for the quantMS workflow
License: MIT
License-File: LICENSE
Keywords: quantms,proteomics,mass-spectrometry,data-analysis,big data
Author: Yasset Perez-Riverol
Author-email: ypriverol@gmail.com
Requires-Python: >=3.9,<3.12
Classifier: Development Status :: 5 - Production/Stable
Classifier: Intended Audience :: Science/Research
Classifier: License :: OSI Approved :: MIT License
Classifier: Operating System :: OS Independent
Classifier: Programming Language :: Python :: 3
Classifier: Programming Language :: Python :: 3.9
Classifier: Programming Language :: Python :: 3.10
Classifier: Programming Language :: Python :: 3.11
Classifier: Programming Language :: Python :: 3 :: Only
Classifier: Topic :: Scientific/Engineering :: Bio-Informatics
Requires-Dist: click
Requires-Dist: deepLC (>=3.0)
Requires-Dist: ms2pip (>=4.0)
Requires-Dist: ms2rescore (==3.2.0.post1)
Requires-Dist: numpy (>=1.25)
Requires-Dist: pandas
Requires-Dist: peptdeep
Requires-Dist: protobuf
Requires-Dist: psm-utils
Requires-Dist: psutil
Requires-Dist: pygam
Requires-Dist: pyopenms (==3.4.0)
Requires-Dist: scipy
Project-URL: GitHub, https://github.com/bigbio/quantms-rescoring
Project-URL: LICENSE, https://github.com/bigbio/quantms-rescoring/blob/main/LICENSE
Project-URL: PyPi, https://pypi.org/project/quantms-rescoring/
Project-URL: Quantms, https://quantms.org
